poplar_isocc/__init__.py
poplar_isocc/expi.json
poplar_isocc/vi/POPISOCC.vi
poplar_isocc-0.3.8.dist-info/LICENSE.txt
poplar_isocc-0.3.8.dist-info/METADATA
poplar_isocc-0.3.8.dist-info/WHEEL
poplar_isocc-0.3.8.dist-info/top_level.txt
poplar_isocc-0.3.8.dist-info/RECORD
